{"name":"hs_device_list_responded","scope":"device","source":"hs","home_id":"hs-b8:27:eb:6c:b4:2b:1607448281692","client_id":"hs-b8:27:eb:6c:b4:2b:1607448281692","user_id":"ngale@homatechs.com","id":"2a1ad64a-d83c-11ed-9b58-b827eb6cb42b","auth_token":"","parent_id":"4a859a56-fe1e-4705-953b-9977943d5a8b","created_time":1681198843439,"data":{"device_list":[{"device_version":3270384805,"device_state":{"device_id":"rasp-gatewayrelay-29110","attributes":{"rl1":false}},"device_profile":{"status":0,"device_id":"rasp-gatewayrelay-29110","device_name":"Den Nha Kho","usage_type":0,"device_type":101,"appliance_type":0,"gateway_device_type":1,"device_mac":"relay-29","gateway_type":20,"gateway_mac":"rasp-gateway","home_id":"hs-b8:27:eb:6c:b4:2b:1607448281692","zone_id":"41e7eb22-397a-11eb-86db-b827eb39e17e","icon_name":"","position":0,"visible":true,"connected":true,"enable_favourite":false,"enable_automation":false,"enable_security":false,"controllable":true,"attributes":{}}},{"device_version":3239506869,"device_state":{"device_id":"rasp-gatewayrelay-28110","attributes":{"rl1":false}},"device_profile":{"status":0,"device_id":"rasp-gatewayrelay-28110","device_name":"Bom Nha Kho","usage_type":0,"device_type":101,"appliance_type":0,"gateway_device_type":1,"device_mac":"relay-28","gateway_type":20,"gateway_mac":"rasp-gateway","home_id":"hs-b8:27:eb:6c:b4:2b:1607448281692","zone_id":"41e7eb22-397a-11eb-86db-b827eb39e17e","icon_name":"","position":0,"visible":true,"connected":true,"enable_favourite":false,"enable_automation":false,"enable_security":false,"controllable":true,"attributes":{}}},{"device_version":3558783255,"device_state":{"device_id":"rasp-gatewayrelay-25110","attributes":{"rl1":true}},"device_profile":{"status":0,"device_id":"rasp-gatewayrelay-25110","device_name":"Bom Nha","usage_type":0,"device_type":101,"appliance_type":0,"gateway_device_type":1,"device_mac":"relay-25","gateway_type":20,"gateway_mac":"rasp-gateway","home_id":"hs-b8:27:eb:6c:b4:2b:1607448281692","zone_id":"41e7eb22-397a-11eb-86db-b827eb39e17e","icon_name":"","position":0,"visible":true,"connected":true,"enable_favourite":false,"enable_automation":false,"enable_security":false,"controllable":true,"attributes":{}}},{"device_version":3912458076,"device_state":{"device_id":"rasp-gateway08010","attributes":{}},"device_profile":{"status":0,"device_id":"rasp-gateway08010","device_name":"IOT HUB","usage_type":0,"device_type":801,"appliance_type":0,"gateway_device_type":801,"device_mac":"rasp-gateway","gateway_type":20,"gateway_mac":"rasp-gateway","home_id":"hs-b8:27:eb:6c:b4:2b:1607448281692","zone_id":"41e7eb22-397a-11eb-86db-b827eb39e17e","icon_name":"","position":0,"visible":false,"connected":true,"enable_favourite":false,"enable_automation":false,"enable_security":false,"controllable":false,"attributes":{}}},{"device_version":570674791,"device_state":{"device_id":"00_04_4b_e7_5b_32-1610611913741-00000640-0000-40F4-8000-0072000000D5","attributes":{}},"device_profile":{"status":0,"device_id":"00_04_4b_e7_5b_32-1610611913741-00000640-0000-40F4-8000-0072000000D5","device_name":"Nha Kho 2","usage_type":0,"device_type":602,"appliance_type":0,"gateway_device_type":0,"device_mac":"54:f1:5f:13:f9:9a","gateway_type":10,"gateway_mac":"00:04:4b:e6:b8:e7","home_id":"hs-b8:27:eb:6c:b4:2b:1607448281692","zone_id":"41e7eb22-397a-11eb-86db-b827eb39e17e","icon_name":"","position":0,"visible":true,"connected":true,"enable_favourite":false,"enable_automation":false,"enable_security":true,"controllable":false,"attributes":{"is_ok":true,"is_ptz":false,"rectangle_detail":"","ip":"192.168.1.4","id":"00_04_4b_e7_5b_32-1610611913741-00000640-0000-40F4-8000-0072000000D5","error_msg":"","human_detection_enabled":true,"cam_view":false,"video_decoder":2,"full_url":"rtsp://admin:ZLUXYC@192.168.1.4:554","is_audio":false,"face_detection_enabled":false,"password":"ZLUXYC","audio_type":"mulaw","is_onvif":false,"port":554,"audio_decoder":2,"mac_add":"54:f1:5f:13:f9:9a","options":"[\"is_ptz\",\"rectangle_detail\",\"notification_enabled\"]","rectangle_size":0,"url":"rtsp://192.168.1.4:554","onvif":"{\"firmware_version\":\"\",\"hw_id\":\"\",\"manufacturer\":\"\",\"media_url\":\"\",\"model\":\"\",\"onvif_port\":80,\"onvif_profiles\":[],\"presets\":[],\"profiles\":[],\"ptz_url\":\"\",\"serial_number\":\"\"}","type":1,"notification_enabled":true,"write_video":true,"user_name":"admin","offset":0.0,"mount_point":"","mapping_index":255,"sip_user":"","onvif_port":80,"cam_index":1,"connected":true,"config":"","name":"Nha Kho 2"}}},{"device_version":2819049904,"device_state":{"device_id":"00_04_4b_e7_5b_32-1610612251726-00000500-0000-4000-8750-0000000C1000","attributes":{}},"device_profile":{"status":0,"device_id":"00_04_4b_e7_5b_32-1610612251726-00000500-0000-4000-8750-0000000C1000","device_name":"Nha Kho 1","usage_type":0,"device_type":602,"appliance_type":0,"gateway_device_type":0,"device_mac":"b4:c9:b9:ec:d0:34","gateway_type":10,"gateway_mac":"00:04:4b:e6:b8:e7","home_id":"hs-b8:27:eb:6c:b4:2b:1607448281692","zone_id":"41e7eb22-397a-11eb-86db-b827eb39e17e","icon_name":"","position":0,"visible":true,"connected":true,"enable_favourite":false,"enable_automation":false,"enable_security":true,"controllable":false,"attributes":{"is_ok":true,"is_ptz":false,"rectangle_detail":"","ip":"192.168.1.2","id":"00_04_4b_e7_5b_32-1610612251726-00000500-0000-4000-8750-0000000C1000","error_msg":"","human_detection_enabled":true,"cam_view":false,"video_decoder":2,"full_url":"rtsp://admin:PLQGCF@192.168.1.2:554","is_audio":false,"face_detection_enabled":false,"password":"PLQGCF","audio_type":"mulaw","is_onvif":false,"port":554,"audio_decoder":2,"mac_add":"b4:c9:b9:ec:d0:34","options":"[\"is_ptz\",\"rectangle_detail\",\"notification_enabled\"]","rectangle_size":0,"url":"rtsp://192.168.1.2:554","onvif":"{\"firmware_version\":\"\",\"hw_id\":\"\",\"manufacturer\":\"\",\"media_url\":\"\",\"model\":\"\",\"onvif_port\":80,\"onvif_profiles\":[],\"presets\":[],\"profiles\":[],\"ptz_url\":\"\",\"serial_number\":\"\"}","type":1,"notification_enabled":true,"write_video":true,"user_name":"admin","offset":0.0,"mount_point":"","mapping_index":255,"sip_user":"","onvif_port":80,"cam_index":2,"connected":true,"config":"","name":"Nha Kho 1"}}},{"device_version":4266511388,"device_state":{"device_id":"00:04:4b:e6:b8:e706010","attributes":{}},"device_profile":{"status":0,"device_id":"00:04:4b:e6:b8:e706010","device_name":"HMAIBOX","usage_type":0,"device_type":601,"appliance_type":0,"gateway_device_type":601,"device_mac":"00:04:4b:e6:b8:e7","gateway_type":10,"gateway_mac":"00:04:4b:e6:b8:e7","home_id":"hs-b8:27:eb:6c:b4:2b:1607448281692","zone_id":"41e7eb22-397a-11eb-86db-b827eb39e17e","icon_name":"","position":0,"visible":false,"connected":false,"enable_favourite":false,"enable_automation":false,"enable_security":true,"controllable":false,"attributes":{"max_detection_zone":3,"mac":"00:04:4b:e6:b8:e7","heat_map_interval_report":900,"public_ip":"UNKNOWN","free_memory":2149875712,"timezone":25200,"video_info":"[\"749ad7#none\",\"e01616#zone\",\"ffffff#animal\",\"ffe033#door\",\"ff8f8f#human\",\"00cc00#other\"]","local_port":"8112","local_ip":"192.168.1.17","last_file_time":1680112637,"audio_port":"8002","password":"gvK6ihIhRjBH","style_info":"[]","thermal_list_id":"[]","user_name":"homa","web_password":"","save_mac":"00:04:4b:e3:fa:fa","user_list_id":"[\"lethiminhchau0809@gmail.com:0\",\"congngale91@gmail.com:0\",\"ngale@homatechs.com:0\"]","version":"2.0.6","streaming_ip":"192.168.1.17","sip_info":"{ \"local_ip\": \"192.168.1.17\" }","http_port":"8012","public_rtsp_port":"8112","mount_point":"/streaming/channels/","cam_list_id":"[]","cam_count":0,"hw_id":"","is_sip_enabled":false}}},{"device_version":2268204167,"device_state":{"device_id":"00_04_4b_e7_5b_32-1612884533065-00000620-0000-4D30-8000-00A200000001","attributes":{}},"device_profile":{"status":0,"device_id":"00_04_4b_e7_5b_32-1612884533065-00000620-0000-4D30-8000-00A200000001","device_name":"Vuon Thanh Long 1","usage_type":0,"device_type":602,"appliance_type":0,"gateway_device_type":0,"device_mac":"64:f2:fb:a0:b1:97","gateway_type":10,"gateway_mac":"00:04:4b:e6:b8:e7","home_id":"hs-b8:27:eb:6c:b4:2b:1607448281692","zone_id":"41e7eb22-397a-11eb-86db-b827eb39e17e","icon_name":"","position":0,"visible":true,"connected":true,"enable_favourite":false,"enable_automation":false,"enable_security":true,"controllable":false,"attributes":{"is_ok":true,"is_ptz":false,"rectangle_detail":"","ip":"192.168.1.9","id":"00_04_4b_e7_5b_32-1612884533065-00000620-0000-4D30-8000-00A200000001","error_msg":"","human_detection_enabled":true,"cam_view":false,"video_decoder":2,"full_url":"rtsp://admin:VUIHYB@192.168.1.9:554","is_audio":false,"face_detection_enabled":false,"password":"VUIHYB","audio_type":"mulaw","is_onvif":false,"port":554,"audio_decoder":2,"mac_add":"64:f2:fb:a0:b1:97","options":"[\"is_ptz\",\"rectangle_detail\",\"notification_enabled\"]","rectangle_size":0,"url":"rtsp://192.168.1.9:554","onvif":"{\"firmware_version\":\"\",\"hw_id\":\"\",\"manufacturer\":\"\",\"media_url\":\"\",\"model\":\"\",\"onvif_port\":80,\"onvif_profiles\":[],\"presets\":[],\"profiles\":[],\"ptz_url\":\"\",\"serial_number\":\"\"}","type":1,"notification_enabled":true,"write_video":true,"user_name":"admin","offset":0.0,"mount_point":"","mapping_index":255,"sip_user":"","onvif_port":80,"cam_index":3,"connected":true,"config":"","name":"Vuon Thanh Long 1"}}},{"device_version":3176969530,"device_state":{"device_id":"00_04_4b_e7_5b_32-1641093079016-00000830-0000-400E-9000-000B4000000E","attributes":{}},"device_profile":{"status":0,"device_id":"00_04_4b_e7_5b_32-1641093079016-00000830-0000-400E-9000-000B4000000E","device_name":"Vuon Thanh Long 3","usage_type":0,"device_type":602,"appliance_type":0,"gateway_device_type":0,"device_mac":"68:6d:bc:95:bb:a1","gateway_type":10,"gateway_mac":"00:04:4b:e6:b8:e7","home_id":"hs-b8:27:eb:6c:b4:2b:1607448281692","zone_id":"41e7eb22-397a-11eb-86db-b827eb39e17e","icon_name":"","position":0,"visible":true,"connected":true,"enable_favourite":false,"enable_automation":false,"enable_security":true,"controllable":false,"attributes":{"is_ok":true,"is_ptz":false,"rectangle_detail":"0.0,0.0,1.0,1.0","ip":"192.168.1.8","id":"00_04_4b_e7_5b_32-1641093079016-00000830-0000-400E-9000-000B4000000E","error_msg":"","human_detection_enabled":true,"cam_view":false,"video_decoder":2,"full_url":"rtsp://admin:MICRGZ@192.168.1.8:554","is_audio":false,"face_detection_enabled":false,"password":"MICRGZ","audio_type":"mulaw","is_onvif":false,"port":554,"audio_decoder":2,"mac_add":"68:6d:bc:95:bb:a1","options":"[\"is_ptz\",\"rectangle_detail\",\"notification_enabled\"]","rectangle_size":1,"url":"rtsp://192.168.1.8:554","onvif":"{\"firmware_version\":\"\",\"hw_id\":\"\",\"manufacturer\":\"\",\"media_url\":\"\",\"model\":\"\",\"onvif_port\":80,\"onvif_profiles\":[],\"presets\":[],\"profiles\":[],\"ptz_url\":\"\",\"serial_number\":\"\"}","type":1,"notification_enabled":true,"write_video":true,"user_name":"admin","offset":0.0,"mount_point":"","mapping_index":255,"sip_user":"","onvif_port":80,"cam_index":5,"connected":true,"config":"","name":"Vuon Thanh Long 3"}}},{"device_version":962472554,"device_state":{"device_id":"00_04_4b_e7_5b_32-1638677872235-00000007-2000-4004-B000-000006000000","attributes":{}},"device_profile":{"status":0,"device_id":"00_04_4b_e7_5b_32-1638677872235-00000007-2000-4004-B000-000006000000","device_name":"Vuon Thanh Long 2","usage_type":0,"device_type":602,"appliance_type":0,"gateway_device_type":0,"device_mac":"64:f2:fb:c7:15:ff","gateway_type":10,"gateway_mac":"00:04:4b:e6:b8:e7","home_id":"hs-b8:27:eb:6c:b4:2b:1607448281692","zone_id":"41e7eb22-397a-11eb-86db-b827eb39e17e","icon_name":"","position":0,"visible":true,"connected":true,"enable_favourite":false,"enable_automation":false,"enable_security":true,"controllable":false,"attributes":{"is_ok":true,"is_ptz":false,"rectangle_detail":"","ip":"192.168.1.10","id":"00_04_4b_e7_5b_32-1638677872235-00000007-2000-4004-B000-000006000000","error_msg":"","human_detection_enabled":true,"cam_view":false,"video_decoder":2,"full_url":"rtsp://admin:YIVZNO@192.168.1.10:554","is_audio":false,"face_detection_enabled":false,"password":"YIVZNO","audio_type":"mulaw","is_onvif":false,"port":554,"audio_decoder":2,"mac_add":"64:f2:fb:c7:15:ff","options":"[\"is_ptz\",\"rectangle_detail\",\"notification_enabled\"]","rectangle_size":0,"url":"rtsp://192.168.1.10:554","onvif":"{\"firmware_version\":\"\",\"hw_id\":\"\",\"manufacturer\":\"\",\"media_url\":\"\",\"model\":\"\",\"onvif_port\":80,\"onvif_profiles\":[],\"presets\":[],\"profiles\":[],\"ptz_url\":\"\",\"serial_number\":\"\"}","type":1,"notification_enabled":true,"write_video":true,"user_name":"admin","offset":0.0,"mount_point":"","mapping_index":255,"sip_user":"","onvif_port":80,"cam_index":4,"connected":true,"config":"","name":"Vuon Thanh Long 2"}}}],"total_device":10,"version":28045015339}}